fiplcr/__init__.py
fiplcr/config.py
fiplcr/fip_map.py
fiplcr/linear_combination/__init__.py
fiplcr/linear_combination/linear_comb.py
fiplcr/specline/__init__.py
fiplcr/specline/read_abund.py
fiplcr/specline/romannumeral.py
fiplcr/specline/specline.py
fiplcr-1.0.dist-info/LICENSE
fiplcr-1.0.dist-info/METADATA
fiplcr-1.0.dist-info/WHEEL
fiplcr-1.0.dist-info/top_level.txt
fiplcr-1.0.dist-info/RECORD
