Metadata-Version: 2.1
Name: fiplcr
Version: 1.0
Summary: Relative FIP bias diagnostics using linear combinations of spectral lines
Home-page: https://git.ias.u-psud.fr/nzambran/fiplcr
Author: Natalia Zambrana Prado
Author-email: natalia.zambrana-prado@ias.u-psud.fr
License: UNKNOWN
Platform: UNKNOWN
Classifier: Programming Language :: Python :: 3
Classifier: License :: OSI Approved :: GNU General Public License v3 (GPLv3)
Classifier: Operating System :: OS Independent
Classifier: Intended Audience :: Science/Research
Requires-Python: >=3.5
Requires-Dist: ChiantiPy (>=0.11.0)
Requires-Dist: astropy (>=3.0)
Requires-Dist: matplotlib (>=2.0)
Requires-Dist: numpy (>=1.15)
Requires-Dist: scipy (>=1.0)
